pytextnow/TNAPI.py
pytextnow/__init__.py
pytextnow/error.py
pytextnow/login.py
pytextnow/message.py
pytextnow/message_container.py
pytextnow/multi_media_message.py
pytextnow/user_cookies.json
PyTextNow-1.2.0.dist-info/LICENSE
PyTextNow-1.2.0.dist-info/METADATA
PyTextNow-1.2.0.dist-info/WHEEL
PyTextNow-1.2.0.dist-info/top_level.txt
PyTextNow-1.2.0.dist-info/RECORD
