Metadata-Version: 2.1
Name: PyTextNow
Version: 1.2.0
Summary: Texting python package which utilizes TextNow.
Home-page: https://github.com/leogomezz4t/PyTextNow_API
Author: Leo Wu-Gomez
Author-email: leojwu18@gmail.com
License: UNKNOWN
Platform: UNKNOWN
Classifier: Programming Language :: Python :: 3
Classifier: License :: OSI Approved :: MIT License
Classifier: Operating System :: OS Independent
Requires-Python: >=3.6
Requires-Dist: requests (~=2.25.1)
Requires-Dist: setuptools (~=57.0.0)
Requires-Dist: python-dateutil (~=2.8.1)
Requires-Dist: mimetypes
Requires-Dist: cloudscraper (~=1.2.58)
